backboard/__init__.py
backboard/__main__.py
backboard/temp.py
backboard-1.0.5.dist-info/LICENSE
backboard-1.0.5.dist-info/METADATA
backboard-1.0.5.dist-info/WHEEL
backboard-1.0.5.dist-info/entry_points.txt
backboard-1.0.5.dist-info/top_level.txt
backboard-1.0.5.dist-info/RECORD
