Metadata-Version: 2.1
Name: backboard
Version: 1.0.5
Summary: Background noises for your keyboard typing
Home-page: https://github.com/donno2048/BS
Author: Elisha Hollander
License: MIT
Platform: UNKNOWN
Classifier: Programming Language :: Python :: 3
License-File: LICENSE
Requires-Dist: pygame (>=1.9.6)
Requires-Dist: keyboard (>=0.13.5)
Requires-Dist: numpy (>=1.20.3)
Requires-Dist: scipy (>=1.6.3)
